nucleodiver/__init__.py
nucleodiver/calcpie.py
nucleodiver/nucleodiver.py
nucleodiver/nucleodiver_2.py
nucleodiver/nucleodiver_3.py
nucleodiver/nucleodiver_4.py
nucleodiver/params.py
nucleodiver/utils.py
nucleodiver-0.2.1.dist-info/LICENSE
nucleodiver-0.2.1.dist-info/METADATA
nucleodiver-0.2.1.dist-info/WHEEL
nucleodiver-0.2.1.dist-info/entry_points.txt
nucleodiver-0.2.1.dist-info/top_level.txt
nucleodiver-0.2.1.dist-info/RECORD
