Metadata-Version: 2.1
Name: nucleodiver
Version: 0.2.1
Summary: Calculate nucleotide diverity from VCF.
Home-page: https://github.com/KChigira/nucleodiver/
Author: Koki Chigira
Author-email: s211905s@st.go.tuat.ac.jp
License: MIT
License-File: LICENSE
Requires-Dist: pandas
